odoo/addons/privacy/README.rst
odoo/addons/privacy/__init__.py
odoo/addons/privacy/__manifest__.py
odoo/addons/privacy/demo/res_users.xml
odoo/addons/privacy/i18n/de.po
odoo/addons/privacy/i18n/es.po
odoo/addons/privacy/i18n/fr.po
odoo/addons/privacy/i18n/hr.po
odoo/addons/privacy/i18n/it.po
odoo/addons/privacy/i18n/privacy.pot
odoo/addons/privacy/i18n/pt.po
odoo/addons/privacy/i18n/pt_BR.po
odoo/addons/privacy/models/__init__.py
odoo/addons/privacy/models/privacy_activity.py
odoo/addons/privacy/readme/CONFIGURATION.rst
odoo/addons/privacy/readme/CONTRIBUTORS.md
odoo/addons/privacy/readme/DESCRIPTION.md
odoo/addons/privacy/readme/USAGE.md
odoo/addons/privacy/security/data_protection.xml
odoo/addons/privacy/security/ir.model.access.csv
odoo/addons/privacy/static/description/icon.png
odoo/addons/privacy/static/description/icon.svg
odoo/addons/privacy/static/description/index.html
odoo/addons/privacy/views/data_protection_menu_view.xml
odoo/addons/privacy/views/privacy_activity_view.xml
odoo_addon_privacy-18.0.1.0.0.3.dist-info/METADATA
odoo_addon_privacy-18.0.1.0.0.3.dist-info/WHEEL
odoo_addon_privacy-18.0.1.0.0.3.dist-info/top_level.txt
odoo_addon_privacy-18.0.1.0.0.3.dist-info/RECORD
