Metadata-Version: 2.1
Name: odoo-addon-privacy
Version: 18.0.1.0.0.3
Requires-Python: >=3.10
Requires-Dist: odoo==18.0.*
Summary: Provides data privacy and protection features to comply to regulations, such as GDPR.
Home-page: https://github.com/OCA/data-protection
License: AGPL-3
Author: Eficent, Tecnativa, Odoo Community Association (OCA)
Author-email: support@odoo-community.org
Classifier: Programming Language :: Python
Classifier: Framework :: Odoo
Classifier: Framework :: Odoo :: 18.0
Classifier: License :: OSI Approved :: GNU Affero General Public License v3
Classifier: Development Status :: 5 - Production/Stable
